pysersic/__init__.py
pysersic/exceptions.py
pysersic/galfit.py
pysersic/loss.py
pysersic/multiband.py
pysersic/priors.py
pysersic/pysersic.py
pysersic/rendering.py
pysersic/results.py
pysersic-0.1.5.dist-info/LICENSE
pysersic-0.1.5.dist-info/METADATA
pysersic-0.1.5.dist-info/WHEEL
pysersic-0.1.5.dist-info/top_level.txt
pysersic-0.1.5.dist-info/RECORD
