Metadata-Version: 2.1
Name: pysersic
Version: 0.1.5
Summary: A Tool for fitting sersic profiles in python
Author-email: Imad Pasha <imad.pasha@yale.edu>, Tim Miller <timothy.miller@northwestern.edu>
License: MIT License
Requires-Python: >=3.11
License-File: LICENSE
Requires-Dist: numpy
Requires-Dist: scipy
Requires-Dist: matplotlib
Requires-Dist: pandas
Requires-Dist: astropy
Requires-Dist: corner
Requires-Dist: photutils >=0.16
Requires-Dist: jax
Requires-Dist: numpyro
Requires-Dist: arviz
Requires-Dist: tqdm
Requires-Dist: asdf
Requires-Dist: equinox >=0.11
Requires-Dist: interpax
